graphqldoc/__init__.py
graphqldoc/admin.py
graphqldoc/apps.py
graphqldoc/models.py
graphqldoc/query.py
graphqldoc/tests.py
graphqldoc/urls.py
graphqldoc/views.py
graphqldoc/migrations/__init__.py
graphqldoc/static/css/main.css
graphqldoc/static/js/main.js
graphqldoc/templates/base.html
graphqldoc/templates/index.html
graphqldoc/templates/nav.html
graphqldoc/templates/sidenav.html
django_graphqldoc-0.1.1.dist-info/LICENSE
django_graphqldoc-0.1.1.dist-info/METADATA
django_graphqldoc-0.1.1.dist-info/WHEEL
django_graphqldoc-0.1.1.dist-info/top_level.txt
django_graphqldoc-0.1.1.dist-info/RECORD
