Metadata-Version: 2.1
Name: django-graphqldoc
Version: 0.1.1
Summary: GraphQLdoc is a simple Django app to document GraphQL schemas.
Home-page: https://github.com/thecylax/django-graphqldoc
Author: Robson Cardoso dos Santos
Author-email: cardoso.rcs@gmail.com
License: BSD License
Platform: UNKNOWN
Classifier: Environment :: Web Environment
Classifier: Framework :: Django
Classifier: Framework :: Django :: 2.1
Classifier: Intended Audience :: Developers
Classifier: License :: OSI Approved :: BSD License
Classifier: Operating System :: OS Independent
Classifier: Programming Language :: Python
Classifier: Programming Language :: Python :: 3.5
Classifier: Programming Language :: Python :: 3.6
Classifier: Topic :: Internet :: WWW/HTTP
Classifier: Topic :: Internet :: WWW/HTTP :: Dynamic Content
Requires-Dist: gql
